QuadrantAnalysis/__init__.py
QuadrantAnalysis/__main__.py
QuadrantAnalysis/main.py
QuadrantAnalysis/core/GUI_Utils.py
QuadrantAnalysis/core/QuadrantFunctions.py
QuadrantAnalysis/core/Tint_Matlab.py
QuadrantAnalysis/core/__init__.py
QuadrantAnalysis/core/addSessions.py
QuadrantAnalysis/core/default_parameters.py
QuadrantAnalysis/core/filtering.py
QuadrantAnalysis/core/plot_utils.py
QuadrantAnalysis/core/quadrant_utils.py
QuadrantAnalysis/core/settingsWindow.py
QuadrantAnalysis/exporters/Exporter.py
QuadrantAnalysis/exporters/ImageExporter.py
QuadrantAnalysis/exporters/__init__.py
QuadrantAnalysis/exporters/tests/__init__.py
QuadrantAnalysis/exporters/tests/test_csv.py
QuadrantAnalysis/exporters/tests/test_svg.py
QuadrantAnalysis/img/GEBA_Logo.png
QuadrantAnalysis/img/__init__.py
QuadrantAnalysis-1.0.3.dist-info/LICENSE
QuadrantAnalysis-1.0.3.dist-info/METADATA
QuadrantAnalysis-1.0.3.dist-info/WHEEL
QuadrantAnalysis-1.0.3.dist-info/top_level.txt
QuadrantAnalysis-1.0.3.dist-info/RECORD
